Workbook

Sheet Sales_Data
A1: Order_ID | B1: Order_Date | C1: Customer_Name | D1: City | E1: State | F1: Product | G1: Category | H1: Quantity | I1: Unit_Price | J1: Discount_% | K1: Gross_Sales | L1: Discount_Amount | M1: Net_Sales | N1: Sales_Channel | O1: Payment_Method | P1: Order_Status | Q1: Salesperson | R1: Sales Performance | S1: Column1
A2: ORD0049 | B2: 46254 | C2: Aarav Agarwal | D2: Delhi | E2: Delhi | F2: Smartphone | G2: Electronics | H2: 2 | I2: 26660 | J2: 0.15 | K2: 53320 | L2: 7998 | M2: 45322 | N2: Mobile App | O2: Net Banking | P2: Delivered | Q2: Aman | R2: =IF(M2>=50000,"High","Low") -> Low | S2: =IF(M2>=50000,"High",IF(M2>=25000,"Medium","Low")) -> Medium
A3: ORD0058 | B3: 46152 | C3: Aarav Patel | D3: Noida | E3: Uttar Pradesh | F3: Power Bank | G3: Accessories | H3: 4 | I3: 1650 | J3: 0 | K3: 6600 | L3: 0 | M3: 6600 | N3: Mobile App | O3: UPI | P3: Delivered | Q3: Deepak | R3: =IF(M3>=50000,"High","Low") -> Low | S3: =IF(M3>=50000,"High",IF(M3>=25000,"Medium","Low")) -> Low
A4: ORD0025 | B4: 46086 | C4: Aditya Agarwal | D4: Lucknow | E4: Uttar Pradesh | F4: Monitor | G4: Electronics | H4: 4 | I4: 11090 | J4: 0.2 | K4: 44360 | L4: 8872 | M4: 35488 | N4: Website | O4: Net Banking | P4: Delivered | Q4: Esha | R4: =IF(M4>=50000,"High","Low") -> Low | S4: =IF(M4>=50000,"High",IF(M4>=25000,"Medium","Low")) -> Medium
A5: ORD0095 | B5: 46183 | C5: Aditya Gupta | D5: Kanpur | E5: Uttar Pradesh | F5: Speaker | G5: Electronics | H5: 3 | I5: 3110 | J5: 0.05 | K5: 9330 | L5: 466.5 | M5: 8863.5 | N5: Mobile App | O5: UPI | P5: Delivered | Q5: Esha | R5: =IF(M5>=50000,"High","Low") -> Low | S5: =IF(M5>=50000,"High",IF(M5>=25000,"Medium","Low")) -> Low
A6: ORD0085 | B6: 46242 | C6: Aditya Mishra | D6: Noida | E6: Uttar Pradesh | F6: Mouse | G6: Accessories | H6: 2 | I6: 710 | J6: 0.05 | K6: 1420 | L6: 71 | M6: 1349 | N6: Marketplace | O6: Net Banking | P6: Delivered | Q6: Deepak | R6: =IF(M6>=50000,"High","Low") -> Low | S6: =IF(M6>=50000,"High",IF(M6>=25000,"Medium","Low")) -> Low
A7: ORD0054 | B7: 46080 | C7: Aditya Sharma | D7: Prayagraj | E7: Uttar Pradesh | F7: Power Bank | G7: Accessories | H7: 1 | I7: 1760 | J7: 0.1 | K7: 1760 | L7: 176 | M7: 1584 | N7: Website | O7: Credit Card | P7: Delivered | Q7: Aman | R7: =IF(M7>=50000,"High","Low") -> Low | S7: =IF(M7>=50000,"High",IF(M7>=25000,"Medium","Low")) -> Low
A8: ORD0068 | B8: 46170 | C8: Aditya Singh | D8: Jaipur | E8: Rajasthan | F8: Headphones | G8: Electronics | H8: 1 | I8: 2450 | J8: 0 | K8: 2450 | L8: 0 | M8: 2450 | N8: Website | O8: Cash on Delivery | P8: Delivered | Q8: Chetan | R8: =IF(M8>=50000,"High","Low") -> Low | S8: =IF(M8>=50000,"High",IF(M8>=25000,"Medium","Low")) -> Low
A9: ORD0073 | B9: 46234 | C9: Aditya Singh | D9: Lucknow | E9: Uttar Pradesh | F9: Power Bank | G9: Accessories | H9: 2 | I9: 1650 | J9: 0.1 | K9: 3300 | L9: 330 | M9: 2970 | N9: Mobile App | O9: Cash on Delivery | P9: Delivered | Q9: Esha | R9: =IF(M9>=50000,"High","Low") -> Low | S9: =IF(M9>=50000,"High",IF(M9>=25000,"Medium","Low")) -> Low
A10: ORD0007 | B10: 46079 | C10: Aditya Verma | D10: Kanpur | E10: Uttar Pradesh | F10: Keyboard | G10: Accessories | H10: 4 | I10: 1170 | J10: 0.2 | K10: 4680 | L10: 936 | M10: 3744 | N10: Website | O10: Debit Card | P10: Delivered | Q10: Deepak | R10: =IF(M10>=50000,"High","Low") -> Low | S10: =IF(M10>=50000,"High",IF(M10>=25000,"Medium","Low")) -> Low
A11: ORD0030 | B11: 46152 | C11: Aditya Yadav | D11: Bhopal | E11: Madhya Pradesh | F11: Mouse | G11: Accessories | H11: 3 | I11: 660 | J11: 0.1 | K11: 1980 | L11: 198 | M11: 1782 | N11: Marketplace | O11: Net Banking | P11: Delivered | Q11: Chetan | R11: =IF(M11>=50000,"High","Low") -> Low | S11: =IF(M11>=50000,"High",IF(M11>=25000,"Medium","Low")) -> Low
A12: ORD0084 | B12: 46160 | C12: Amit Tiwari | D12: Bhopal | E12: Madhya Pradesh | F12: External HDD | G12: Electronics | H12: 4 | I12: 6970 | J12: 0.15 | K12: 27880 | L12: 4182 | M12: 23698 | N12: Marketplace | O12: Net Banking | P12: Delivered | Q12: Deepak | R12: =IF(M12>=50000,"High","Low") -> Low | S12: =IF(M12>=50000,"High",IF(M12>=25000,"Medium","Low")) -> Low
A13: ORD0003 | B13: 46094 | C13: Amit Yadav | D13: Agra | E13: Uttar Pradesh | F13: Laptop | G13: Electronics | H13: 2 | I13: 57180 | J13: 0.1 | K13: 114360 | L13: 11436 | M13: 102924 | N13: Website | O13: Net Banking | P13: Delivered | Q13: Aman | R13: =IF(M13>=50000,"High","Low") -> High | S13: =IF(M13>=50000,"High",IF(M13>=25000,"Medium","Low")) -> High
... A101: ORD0074 | B101: 46202 | C101: Vikas Tiwari | D101: Agra | E101: Uttar Pradesh | F101: Pen Set | G101: Stationery | H101: 1 | I101: 250 | J101: 0.1 | K101: 250 | L101: 25 | M101: 225 | N101: Marketplace | O101: Net Banking | P101: Delivered | Q101: Deepak | R101: =IF(M101>=50000,"High","Low") -> Low | S101: =IF(M101>=50000,"High",IF(M101>=25000,"Medium","Low")) -> Low
A103: Counta | C103: =C2&":"&D2&"-"&E2 -> Aarav Agarwal:Delhi-Delhi | H103: =SUM([1]Sales_Data!H2:H101) -> 276 | K103: Total | M103: Total | N103: marketplace | P103: returned
A104: =COUNTA(A2:A101) -> 100 | C104: =C3&":"&D3 -> Aarav Patel:Noida | E104: uttar Pradesh & Accessories | K104: =SUM([1]Sales_Data!K2:K101) -> 2955590 | M104: =SUM([1]Sales_Data!M2:M101) -> 2764145 | N104: =COUNTIF(N2:N101,"marketplace") -> 32 | P104: =COUNTIF(P2:P101,"returned") -> 4
C105: =C4&":"&D4 -> Aditya Agarwal:Lucknow | E105: =COUNTIFS(Sales_Data!E2:E101,"uttar pradesh",Sales_Data!G2:G101,"accessories") -> 15 | M105: Average | N105: mobile app | P105: cancled
C106: =C5&":"&D5 -> Aditya Gupta:Kanpur | E106: uttar Pradesh & Electronics | M106: =AVERAGE([1]Sales_Data!M2:M101) -> 27641.45 | N106: =COUNTIF(N2:N101,"mobile app") -> 34 | P106: =COUNTIF(P2:P101,"cancelled") -> 6
C107: =C6&":"&D6 -> Aditya Mishra:Noida | E107: =COUNTIFS(Sales_Data!E2:E101,"uttar pradesh",Sales_Data!G2:G101,"Electronics") -> 25 | M107: highest | N107: website | P107: delivered
C108: =C7&":"&D7 -> Aditya Sharma:Prayagraj | E108: Bihar & Electronics | M108: =MAX(Sales_Data[Net_Sales]) -> 299650 | N108: =COUNTIF(N2:N101,"website") -> 34 | P108: =COUNTIF(P2:P101,"delivered") -> 87
C109: =C8&":"&D8 -> Aditya Singh:Jaipur | E109: =COUNTIFS(Sales_Data!E3:E102,"Bihar",Sales_Data!G3:G102,"Electronics") -> 8 | M109: smallest | P109: shipped
C110: =C9&":"&D9 -> Aditya Singh:Lucknow | L110: Stationery | M110: =MIN(M2:M101) -> 180 | P110: =COUNTIF(P2:P101,"shipped") -> 3
C111: =C10&":"&D10 -> Aditya Verma:Kanpur | L111: =SUMIF(Sales_Data!G2:G101,"Stationery",Sales_Data!M2:M101) -> 7978.5 | M111: Greater Than 10000 & Smaller Than 40000 | P111: Delivered & Website
C112: =C11&":"&D11 -> Aditya Yadav:Bhopal | L112: Electronics | M112: =COUNTIFS(Sales_Data!M11:M110,">=10000",Sales_Data!M11:M110,"<=40000") -> 22 | P112: =COUNTIFS(Sales_Data!P2:P101,"Delivered",Sales_Data!N2:N101,"Website") -> 31
C113: =C12&":"&D12 -> Amit Tiwari:Bhopal | L113: =SUMIF(Sales_Data!G4:G103,"Electronics",Sales_Data!M4:M103) -> 2413485 | M113: Greater Than 10000
C114: =C13&":"&D13 -> Amit Yadav:Agra | L114: Aceessories | M114: =COUNTIF(Sales_Data!M2:M101,">=10000") -> 39
C115: =C14&":"&D14 -> Amit Yadav:Delhi | L115: =SUMIF(Sales_Data!G6:G105,"Accessories",Sales_Data!M6:M105) -> 67909.5 | M115: < 10000 & > 50000
C116: =C15&":"&D15 -> Amit Yadav:Patna | M116: =COUNTIFS(Sales_Data!M2:M101,">=10000",Sales_Data!M2:M101,"<=50000") -> 27
C117: =C16&":"&D16 -> Ananya Agarwal:Agra
C118: =C17&":"&D17 -> Ananya Tiwari:Jaipur
C119: =C18&":"&D18 -> Ananya Verma:Lucknow

Sheet Total Sales
A1: Row Labels | B1: Sum of Net_Sales
A2: Accessories | B2: 74509.5
A3: Electronics | B3: 2458807
A4: Furniture | B4: 222850
A5: Stationery | B5: 7978.5
A6: Grand Total | B6: 2764145
A15: Row Labels | B15: Count of Net_Sales
A16: Agra | B16: 15
A17: Bhopal | B17: 8
A18: Delhi | B18: 12
A19: Jaipur | B19: 10
A20: Kanpur | B20: 7
A21: Lucknow | B21: 10
A22: Noida | B22: 12
A23: Patna | B23: 11
A24: Prayagraj | B24: 9
A25: Varanasi | B25: 6
A26: Grand Total | B26: 100
A33: Row Labels | B33: Sum of Net_Sales
A34: Aarav Agarwal | B34: 45322
A35: Amit Yadav | B35: 136988
A36: Ananya Verma | B36: 3827
A37: Arjun Tiwari | B37: 118750
A38: Ishita Yadav | B38: 32210
A39: Karan Tiwari | B39: 10782
A40: Mohit Gupta | B40: 3655
A41: Nisha Kumar | B41: 11840
A42: Pooja Agarwal | B42: 94237.5
A43: Priya Kumar | B43: 26902.5
A44: Simran Mishra | B44: 5895
A45: Vikas Agarwal | B45: 2116.5
... A47: Grand Total | B47: 492750.5

Sheet Month Wise Sales
A1: Row Labels | B1: Sum of Net_Sales
A2: Jan | B2: 525982.5
A3: Feb | B3: 203187
A4: Mar | B4: 569955
A5: Apr | B5: 187843.5
A6: May | B6: 431359
A7: Jun | B7: 123646.5
A8: Jul | B8: 350634.5
A9: Aug | B9: 371537
A10: Grand Total | B10: 2764145
A15: State | B15: Sales
A16: Uttar Pradesh | B16: =SUMIF(Sales_Data!E:E,A16,Sales_Data!M:M) -> 1280588
A17: Rajasthan | B17: =SUMIF(Sales_Data!E:E,A17,Sales_Data!M:M) -> 354412
A18: Delhi | B18: =SUMIF(Sales_Data!E:E,A18,Sales_Data!M:M) -> 134788.5
A19: Bihar | B19: =SUMIF(Sales_Data!E:E,A19,Sales_Data!M:M) -> 901482.5
A20: Madhya Pradesh | B20: =SUMIF(Sales_Data!E:E,A20,Sales_Data!M:M) -> 92874
